oncourse_api/__init__.py
oncourse_api/errors.py
oncourse_api/oncourse.py
oncourse_api/models/__init__.py
oncourse_api/models/active_profile.py
oncourse_api/models/assignment.py
oncourse_api/models/group.py
oncourse_api/models/student.py
oncourse_api-2.2.1.dist-info/METADATA
oncourse_api-2.2.1.dist-info/WHEEL
oncourse_api-2.2.1.dist-info/top_level.txt
oncourse_api-2.2.1.dist-info/RECORD
