Metadata-Version: 2.1
Name: oncourse-api
Version: 2.2.1
Summary: A python api wrapper for OnCourse Connect
Home-page: https://github.com/Wolfhound905/OnCourse-API
Author: Wolfhound905
Author-email: aiden8green@gmail.com
License: MIT
Platform: UNKNOWN
Classifier: Programming Language :: Python :: 3
Classifier: License :: OSI Approved :: MIT License
Classifier: Operating System :: OS Independent
Requires-Dist: requests
Requires-Dist: tomli
